Classfile /home/asd/workspaceExercises/java-certification/generics/overloading/GenericOverloadingString.class
  Last modified May 6, 2023; size 281 bytes
  SHA-256 checksum 753fa7c80cf656fbff557b4cce41487d97fbf423d94faa72ee3ae77ec3e526dd
  Compiled from "GenericOverloading.java"
class GenericOverloadingString extends GenericOverloading<java.lang.String>
  minor version: 0
  major version: 61
  flags: (0x0020) ACC_SUPER
  this_class: #7                          // GenericOverloadingString
  super_class: #2                         // GenericOverloading
  interfaces: 0, fields: 0, methods: 1, attributes: 2
Constant pool:
   #1 = Methodref          #2.#3          // GenericOverloading."<init>":()V
   #2 = Class              #4             // GenericOverloading
   #3 = NameAndType        #5:#6          // "<init>":()V
   #4 = Utf8               GenericOverloading
   #5 = Utf8               <init>
   #6 = Utf8               ()V
   #7 = Class              #8             // GenericOverloadingString
   #8 = Utf8               GenericOverloadingString
   #9 = Utf8               Code
  #10 = Utf8               LineNumberTable
  #11 = Utf8               Signature
  #12 = Utf8               LGenericOverloading<Ljava/lang/String;>;
  #13 = Utf8               SourceFile
  #14 = Utf8               GenericOverloading.java
{
  GenericOverloadingString();
    descriptor: ()V
    flags: (0x0000)
    Code:
      stack=1, locals=1, args_size=1
         0: aload_0
         1: invokespecial #1                  // Method GenericOverloading."<init>":()V
         4: return
      LineNumberTable:
        line 40: 0
}
Signature: #12                          // LGenericOverloading<Ljava/lang/String;>;
SourceFile: "GenericOverloading.java"
